blch/__init__.py
blch/blchmod.py
blch-0.5.0.dist-info/METADATA
blch-0.5.0.dist-info/WHEEL
blch-0.5.0.dist-info/top_level.txt
blch-0.5.0.dist-info/RECORD
